scrapy_settings_log/__init__.py
scrapy_settings_log-1.4.0.dist-info/LICENSE
scrapy_settings_log-1.4.0.dist-info/METADATA
scrapy_settings_log-1.4.0.dist-info/WHEEL
scrapy_settings_log-1.4.0.dist-info/top_level.txt
scrapy_settings_log-1.4.0.dist-info/RECORD
