Metadata-Version: 2.1
Name: scrapy-settings-log
Version: 1.4.0
Summary: An extension that allows a user to display all or some of their scrapy spider settings at runtime.
Home-page: https://github.com/scrapy-plugins/scrapy-settings-log
Author: Roy Healy
Author-email: roy.healy87@gmail.com
Project-URL: repository, https://github.com/scrapy-plugins/scrapy-settings-log
Classifier: Programming Language :: Python :: 3
Classifier: License :: OSI Approved :: MIT License
Classifier: Operating System :: OS Independent
Requires-Python: >=3.8
License-File: LICENSE
Requires-Dist: scrapy
